dep_scanner/__init__.py
dep_scanner/cli.py
dep_scanner/exceptions.py
dep_scanner/file_type_detector.py
dep_scanner/file_utils.py
dep_scanner/scanner.py
dep_scanner/analyzers/__init__.py
dep_scanner/analyzers/analyzer_manager.py
dep_scanner/analyzers/base.py
dep_scanner/analyzers/java_analyzer.py
dep_scanner/analyzers/python_analyzer.py
dep_scanner/normalizers/__init__.py
dep_scanner/normalizers/java_package.py
dep_scanner/normalizers/python_package.py
dep_scanner/parsers/__init__.py
dep_scanner/parsers/base.py
dep_scanner/parsers/build_sbt.py
dep_scanner/parsers/conda_environment.py
dep_scanner/parsers/gradle_build.py
dep_scanner/parsers/maven_pom.py
dep_scanner/parsers/parser_manager.py
dep_scanner/parsers/pip_dependencies.py
dep_scanner/parsers/pyproject_toml.py
dep_scanner/parsers/requirements_txt.py
rajverma_dep_scanner-0.1.0.dist-info/METADATA
rajverma_dep_scanner-0.1.0.dist-info/WHEEL
rajverma_dep_scanner-0.1.0.dist-info/entry_points.txt
rajverma_dep_scanner-0.1.0.dist-info/RECORD
